download_images/__init__.py
download_images/download_images.py
download_images_Xarcrax-1.0.2.dist-info/METADATA
download_images_Xarcrax-1.0.2.dist-info/WHEEL
download_images_Xarcrax-1.0.2.dist-info/top_level.txt
download_images_Xarcrax-1.0.2.dist-info/RECORD
