Metadata-Version: 2.1
Name: download-images-Xarcrax
Version: 1.0.2
Summary: Package that downloads images from google
Home-page: https://github.com/Xarcrax/download_images
Author: Akhilesh Chandorkar
Author-email: akhilesh.chandorkar@gmail.com
License: UNKNOWN
Project-URL: Bug Reports, https://github.com/Xarcrax/download_images/issues
Project-URL: Buy me a coffee, https://ko-fi.com/xarcrax
Project-URL: Say Thanks!, https://saythanks.io/to/akhilesh.chandorkar%40gmail.com
Project-URL: Source, https://github.com/Xarcrax/download_images/sampleproject/
Keywords: images,download,google
Platform: UNKNOWN
Classifier: Programming Language :: Python :: 3
Classifier: License :: OSI Approved :: MIT License
Classifier: Operating System :: OS Independent
Requires-Python: >=3.6
Requires-Dist: selenium
